{
    "navbar": {
        "projects": "Projects",
        "about": "About",
        "tech_tendencies": "Tech Tendencies",
        "contact": "Contact"
    },
    "bannerSection": {
        "jobTitle": "frontend developer at looqbox",
        "textRows": [
            "Turning inspiring",
            "digital experiences",
            "into",
            "reality"
        ],
        "button": "Explore"
    },
    "projectSection": {
        "nasa": {
            "title": "Nasa APIs",
            "description": "🛰️ Nasa APIs - is a platform that aims to use some of the APIs provided by NASA to extract interesting data about the universe."
        },
        "todoList": {
            "title": "Todo List",
            "description": "Simple todo list app with filters, tags and offline concepts"
        },
        "tonyMoedas": {
            "title": "Tony Moedas",
            "description": "Crypto app, listing cryptocoins and showing trading charts"
        }
    },
    "aboutSection": {
        "miniBio": {
            "title": "Antonio Gally",
            "description": "Frontend developer at Looqbox, Computer Science student at Impacta and technology enthusiast. I'm currently focused on web and mobile development, but I'm also interested in DevOps and security."
        },
        "fullBio": {
            "title": "Professional me",
            "description01": "My background is primarily in startups, so I learn quickly, am dynamic, work well in teams, and can adapt to any stack or area. Throughout my career, I've had a strong focus on frontend development, especially using technologies like React and React Native.",
            "description02": "I also have skills in backend development; I'm currently studying microservices, authentication, proxies, gateways, among others. I've been exploring DevOps extensively, studying Docker, Kubernetes, GCP, Jenkins, GitHub Actions, and security tools.",
            "button": "My Github"
        }
    },
    "contactSection": {
        "title": "Up for a talk?",
        "email": "Email",
        "message": "Message",
        "button": "Send"
    },
    "footer": {
        "developed": "Developed by Antonio Gally",
        "designed": "Designed by Andre Alcantara"
    }
}